ezmsg/lsl/__init__.py
ezmsg/lsl/__version__.py
ezmsg/lsl/inlet.py
ezmsg/lsl/outlet.py
ezmsg/lsl/units.py
ezmsg/lsl/util.py
ezmsg_lsl-1.4.3.dist-info/METADATA
ezmsg_lsl-1.4.3.dist-info/WHEEL
ezmsg_lsl-1.4.3.dist-info/licenses/LICENSE
ezmsg_lsl-1.4.3.dist-info/RECORD
