Metadata-Version: 2.4
Name: ezmsg-lsl
Version: 1.4.3
Summary: LabStreamingLayer source and sink for ezmsg
Author-email: Chadwick Boulay <chadwick.boulay@gmail.com>
License-File: LICENSE
Requires-Python: >=3.10.15
Requires-Dist: ezmsg>=3.6.0
Requires-Dist: numpy>=1.26.4
Requires-Dist: pylsl>=1.18.1
